[{"name":"","steps":[{"number":1,"step":"Flake crab with 1 t lemon juice in large bowl.","ingredients":[{"id":9152,"name":"lemon juice","localizedName":"lemon juice","image":"lemon-juice.jpg"},{"id":15136,"name":"crab","localizedName":"crab","image":"crabmeat.jpg"}],"equipment":[{"id":404783,"name":"bowl","localizedName":"bowl","image":"bowl.jpg"}]},{"number":2,"step":"Add onion, celery (optional), vinegar, soy sauce, worcestershire, and 1 t dill.Stir until mixed.Stir in mayonnaise (adjust amount according to taste).","ingredients":[{"id":6971,"name":"worcestershire sauce","localizedName":"worcestershire sauce","image":"dark-sauce.jpg"},{"id":4025,"name":"mayonnaise","localizedName":"mayonnaise","image":"mayonnaise.png"},{"id":16124,"name":"soy sauce","localizedName":"soy sauce","image":"soy-sauce.jpg"},{"id":2053,"name":"vinegar","localizedName":"vinegar","image":"vinegar-(white).jpg"},{"id":11143,"name":"celery","localizedName":"celery","image":"celery.jpg"},{"id":11282,"name":"onion","localizedName":"onion","image":"brown-onion.png"},{"id":2045,"name":"dill","localizedName":"dill","image":"dill.jpg"}],"equipment":[]},{"number":3,"step":"Add salt and pepper to taste.Slice avocado into bitesize pieces and sprinkle with remaining 1 t lemon juice (keeps avocado from browning) and 1/2 t dill.Gently stir avocados and olives into the salad.Taste and adjust seasonings as needed.","ingredients":[{"id":1102047,"name":"salt and pepper","localizedName":"salt and pepper","image":"salt-and-pepper.jpg"},{"id":9152,"name":"lemon juice","localizedName":"lemon juice","image":"lemon-juice.jpg"},{"id":1042027,"name":"seasoning","localizedName":"seasoning","image":"seasoning.png"},{"id":9037,"name":"avocado","localizedName":"avocado","image":"avocado.jpg"},{"id":9195,"name":"olives","localizedName":"olives","image":"olives-mixed.jpg"},{"id":2045,"name":"dill","localizedName":"dill","image":"dill.jpg"}],"equipment":[]},{"number":4,"step":"Serve or refrigerate for several hours.","ingredients":[],"equipment":[]}]}]
