[{"name":"","steps":[{"number":1,"step":"Preheat oven to 425F.  Toss vegetables with dressing.","ingredients":[{"id":11583,"name":"vegetable","localizedName":"vegetable","image":"mixed-vegetables.png"}],"equipment":[{"id":404784,"name":"oven","localizedName":"oven","image":"oven.jpg","temperature":{"number":425.0,"unit":"Fahrenheit"}}]},{"number":2,"step":"Spread evenly into 15x10x1-inch baking pan sprayed with cooking spray.","ingredients":[{"id":4679,"name":"cooking spray","localizedName":"cooking spray","image":"cooking-spray.png"},{"id":0,"name":"spread","localizedName":"spread","image":""}],"equipment":[{"id":404646,"name":"baking pan","localizedName":"baking pan","image":"roasting-pan.jpg"}]},{"number":3,"step":"Bake 45 min. or until vegetables are tender and golden brown, stirring after 30 min.","ingredients":[{"id":11583,"name":"vegetable","localizedName":"vegetable","image":"mixed-vegetables.png"}],"equipment":[{"id":404784,"name":"oven","localizedName":"oven","image":"oven.jpg"}],"length":{"number":75,"unit":"minutes"}}]}]
