[{"name":"","steps":[{"number":1,"step":"In a food processor, combine the beans, olives, oil, parsley, lemon juice, honey, lemon zest, rosemary, and salt. Blend until smooth.","ingredients":[{"id":9152,"name":"lemon juice","localizedName":"lemon juice","image":"lemon-juice.jpg"},{"id":9156,"name":"lemon zest","localizedName":"lemon zest","image":"zest-lemon.jpg"},{"id":2036,"name":"rosemary","localizedName":"rosemary","image":"rosemary.jpg"},{"id":11297,"name":"parsley","localizedName":"parsley","image":"parsley.jpg"},{"id":9195,"name":"olives","localizedName":"olives","image":"olives-mixed.jpg"},{"id":0,"name":"beans","localizedName":"beans","image":"kidney-beans.jpg"},{"id":19296,"name":"honey","localizedName":"honey","image":"honey.png"},{"id":2047,"name":"salt","localizedName":"salt","image":"salt.jpg"},{"id":4582,"name":"cooking oil","localizedName":"cooking oil","image":"vegetable-oil.jpg"}],"equipment":[{"id":404771,"name":"food processor","localizedName":"food processor","image":"food-processor.png"}]},{"number":2,"step":"Spread the tapenade onto Belgian endive spears or serve as a dip with crudite.","ingredients":[{"id":11151,"name":"belgian endive","localizedName":"belgian endive","image":"chicory.jpg"},{"id":0,"name":"tapenade","localizedName":"tapenade","image":""},{"id":0,"name":"spread","localizedName":"spread","image":""},{"id":0,"name":"dip","localizedName":"dip","image":""}],"equipment":[]}]}]
