[{"name":"","steps":[{"number":1,"step":"In a small bowl, combine olive oil, lime juice, soy sauce, chili powder, cumin and garlic. Season fish on all sides with salt and pepper and place in a dish large enough to hold in a single layer.","ingredients":[{"id":1102047,"name":"salt and pepper","localizedName":"salt and pepper","image":"salt-and-pepper.jpg"},{"id":2009,"name":"chili powder","localizedName":"chili powder","image":"chili-powder.jpg"},{"id":9160,"name":"lime juice","localizedName":"lime juice","image":"lime-juice.png"},{"id":4053,"name":"olive oil","localizedName":"olive oil","image":"olive-oil.jpg"},{"id":16124,"name":"soy sauce","localizedName":"soy sauce","image":"soy-sauce.jpg"},{"id":11215,"name":"garlic","localizedName":"garlic","image":"garlic.png"},{"id":1002014,"name":"cumin","localizedName":"cumin","image":"ground-cumin.jpg"},{"id":10115261,"name":"fish","localizedName":"fish","image":"fish-fillet.jpg"}],"equipment":[{"id":404783,"name":"bowl","localizedName":"bowl","image":"bowl.jpg"}]},{"number":2,"step":"Pour marinade over fish, cover and refrigerate for 15 to 20 minutes.","ingredients":[{"id":0,"name":"marinade","localizedName":"marinade","image":"seasoning.png"},{"id":10115261,"name":"fish","localizedName":"fish","image":"fish-fillet.jpg"}],"equipment":[],"length":{"number":15,"unit":"minutes"}},{"number":3,"step":"Preheat gas grill to medium, or preheat broiler to high and set rack 6 inches from source of heat.","ingredients":[],"equipment":[{"id":405914,"name":"broiler","localizedName":"broiler","image":"oven.jpg"},{"id":404706,"name":"grill","localizedName":"grill","image":"grill.jpg"}]},{"number":4,"step":"Remove fish from marinade and grill or broil until flaky, 2 to 3 minutes per side.","ingredients":[{"id":0,"name":"marinade","localizedName":"marinade","image":"seasoning.png"},{"id":10115261,"name":"fish","localizedName":"fish","image":"fish-fillet.jpg"}],"equipment":[{"id":404706,"name":"grill","localizedName":"grill","image":"grill.jpg"}],"length":{"number":2,"unit":"minutes"}},{"number":5,"step":"Remove to a plate and let rest for 5 minutes, then cut into chunks. Season with salt, pepper and additional lime juice, if desired.","ingredients":[{"id":9160,"name":"lime juice","localizedName":"lime juice","image":"lime-juice.png"},{"id":1002030,"name":"pepper","localizedName":"pepper","image":"pepper.jpg"},{"id":2047,"name":"salt","localizedName":"salt","image":"salt.jpg"}],"equipment":[],"length":{"number":5,"unit":"minutes"}},{"number":6,"step":"Warm tortillas as package label directs.","ingredients":[{"id":18364,"name":"tortilla","localizedName":"tortilla","image":"flour-tortilla.jpg"}],"equipment":[]},{"number":7,"step":"Serve tilapia with tortillas.","ingredients":[{"id":18364,"name":"tortilla","localizedName":"tortilla","image":"flour-tortilla.jpg"},{"id":15261,"name":"tilapia","localizedName":"tilapia","image":"raw-tilapia.jpg"}],"equipment":[]}]}]
