[{"name":"","steps":[{"number":1,"step":"Heat a nonstick skillet or grill pan over medium heat. Coat fish with cooking spray; sprinkle with salt and pepper.","ingredients":[{"id":1102047,"name":"salt and pepper","localizedName":"salt and pepper","image":"salt-and-pepper.jpg"},{"id":4679,"name":"cooking spray","localizedName":"cooking spray","image":"cooking-spray.png"},{"id":10115261,"name":"fish","localizedName":"fish","image":"fish-fillet.jpg"}],"equipment":[{"id":404648,"name":"grill pan","localizedName":"grill pan","image":"grill-pan.jpg"},{"id":404645,"name":"frying pan","localizedName":"frying pan","image":"pan.png"}]},{"number":2,"step":"Add fish to pan; cook 1012 minutes, turning once, until fish flakes easily with a fork.","ingredients":[{"id":10115261,"name":"fish","localizedName":"fish","image":"fish-fillet.jpg"}],"equipment":[{"id":404645,"name":"frying pan","localizedName":"frying pan","image":"pan.png"}],"length":{"number":1012,"unit":"minutes"}},{"number":3,"step":"Combine yogurt and next 5 ingredients (through honey) in a small bowl, stirring with a whisk.","ingredients":[{"id":1116,"name":"yogurt","localizedName":"yogurt","image":"plain-yogurt.jpg"},{"id":19296,"name":"honey","localizedName":"honey","image":"honey.png"}],"equipment":[{"id":404661,"name":"whisk","localizedName":"whisk","image":"whisk.png"},{"id":404783,"name":"bowl","localizedName":"bowl","image":"bowl.jpg"}]},{"number":4,"step":"Combine dressing and coleslaw mix, tossing to coat.","ingredients":[{"id":10011109,"name":"coleslaw mix","localizedName":"coleslaw mix","image":"coleslaw.png"}],"equipment":[]},{"number":5,"step":"Flake fish into pieces with a fork.","ingredients":[{"id":10115261,"name":"fish","localizedName":"fish","image":"fish-fillet.jpg"}],"equipment":[]},{"number":6,"step":"Place 2 ounces fish in each tortilla. Top with coleslaw.","ingredients":[{"id":18364,"name":"tortilla","localizedName":"tortilla","image":"flour-tortilla.jpg"},{"id":10115261,"name":"fish","localizedName":"fish","image":"fish-fillet.jpg"}],"equipment":[]}]}]
