[{"name":"","steps":[{"number":1,"step":"Arrange fish in a single layer in a shallow roasting pan coated with cooking spray.","ingredients":[{"id":4679,"name":"cooking spray","localizedName":"cooking spray","image":"cooking-spray.png"},{"id":10115261,"name":"fish","localizedName":"fish","image":"fish-fillet.jpg"}],"equipment":[{"id":404629,"name":"roasting pan","localizedName":"roasting pan","image":"roasting-pan.jpg"}]},{"number":2,"step":"Combine orange juice and next 9 ingredients (through garlic); pour over fish.","ingredients":[{"id":9206,"name":"orange juice","localizedName":"orange juice","image":"orange-juice.jpg"},{"id":11215,"name":"garlic","localizedName":"garlic","image":"garlic.png"},{"id":10115261,"name":"fish","localizedName":"fish","image":"fish-fillet.jpg"}],"equipment":[]},{"number":3,"step":"Let stand 15 minutes.","ingredients":[],"equipment":[],"length":{"number":15,"unit":"minutes"}},{"number":4,"step":"Preheat broiler.","ingredients":[],"equipment":[{"id":405914,"name":"broiler","localizedName":"broiler","image":"oven.jpg"}]},{"number":5,"step":"Sprinkle fish with paprika; broil 15 minutes or until desired degree of doneness.","ingredients":[{"id":2028,"name":"paprika","localizedName":"paprika","image":"paprika.jpg"},{"id":10115261,"name":"fish","localizedName":"fish","image":"fish-fillet.jpg"}],"equipment":[],"length":{"number":15,"unit":"minutes"}},{"number":6,"step":"Drizzle sauce over fish.","ingredients":[{"id":0,"name":"sauce","localizedName":"sauce","image":""},{"id":10115261,"name":"fish","localizedName":"fish","image":"fish-fillet.jpg"}],"equipment":[]}]}]
