[{"name":"","steps":[{"number":1,"step":"Preheat broiler.","ingredients":[],"equipment":[{"id":405914,"name":"broiler","localizedName":"broiler","image":"oven.jpg"}]},{"number":2,"step":"Combine first 9 ingredients in a food processor; pulse 3 times or until coarsely chopped.","ingredients":[],"equipment":[{"id":404771,"name":"food processor","localizedName":"food processor","image":"food-processor.png"}]},{"number":3,"step":"Place fish on a broiler pan coated with cooking spray; spread 1/2 cup shallot mixture evenly over fish. Broil 15 minutes or until fish flakes easily when tested with a fork.","ingredients":[{"id":4679,"name":"cooking spray","localizedName":"cooking spray","image":"cooking-spray.png"},{"id":11677,"name":"shallot","localizedName":"shallot","image":"shallots.jpg"},{"id":0,"name":"spread","localizedName":"spread","image":""},{"id":10115261,"name":"fish","localizedName":"fish","image":"fish-fillet.jpg"}],"equipment":[{"id":404698,"name":"broiler pan","localizedName":"broiler pan","image":"broiler-pan.jpg"}],"length":{"number":15,"unit":"minutes"}},{"number":4,"step":"Serve the fish with the remaining shallot mixture, and garnish with cilantro sprigs and lemon wedges, if desired.","ingredients":[{"id":1029150,"name":"lemon wedge","localizedName":"lemon wedge","image":"lemon-wedge.png"},{"id":11165,"name":"cilantro","localizedName":"cilantro","image":"cilantro.png"},{"id":11677,"name":"shallot","localizedName":"shallot","image":"shallots.jpg"},{"id":10115261,"name":"fish","localizedName":"fish","image":"fish-fillet.jpg"}],"equipment":[]}]}]
