[{"name":"","steps":[{"number":1,"step":"In a food processor, combine 4 tablespoons of the butter with the tuna and red pepper and process to a coarse puree. Season with salt and pepper.","ingredients":[{"id":1102047,"name":"salt and pepper","localizedName":"salt and pepper","image":"salt-and-pepper.jpg"},{"id":11821,"name":"red pepper","localizedName":"red pepper","image":"red-pepper.jpg"},{"id":1001,"name":"butter","localizedName":"butter","image":"butter-sliced.jpg"},{"id":10015121,"name":"tuna","localizedName":"tuna","image":"canned-tuna.png"}],"equipment":[{"id":404771,"name":"food processor","localizedName":"food processor","image":"food-processor.png"}]},{"number":2,"step":"In a small skillet, melt the remaining 1 tablespoon of butter.","ingredients":[{"id":1001,"name":"butter","localizedName":"butter","image":"butter-sliced.jpg"}],"equipment":[{"id":404645,"name":"frying pan","localizedName":"frying pan","image":"pan.png"}]},{"number":3,"step":"Add the pine nuts and cook over low heat, stirring occasionally, until golden brown, about 3 minutes.","ingredients":[{"id":12147,"name":"pine nuts","localizedName":"pine nuts","image":"pine-nuts.png"}],"equipment":[],"length":{"number":3,"unit":"minutes"}},{"number":4,"step":"Spread about 2 teaspoons of tuna mousse on each toast and transfer to a platter.","ingredients":[{"id":0,"name":"spread","localizedName":"spread","image":""},{"id":18070,"name":"toast","localizedName":"toast","image":"toast"},{"id":10015121,"name":"tuna","localizedName":"tuna","image":"canned-tuna.png"}],"equipment":[]},{"number":5,"step":"Garnish with the toasted pine nuts and serve.","ingredients":[{"id":12147,"name":"pine nuts","localizedName":"pine nuts","image":"pine-nuts.png"}],"equipment":[]}]}]
