[{"name":"","steps":[{"number":1,"step":"Put the tuna in a shallow dish, drizzle over the oil and lemon juice, scatter over the garlic and rosemary. Turn the tuna so its well coated. Cover and put in the fridge for 30 minutes (you can leave it for longer if convenient).Tip the beans into a large bowl. Toss in the tomatoes, onion and rocket.","ingredients":[{"id":9152,"name":"lemon juice","localizedName":"lemon juice","image":"lemon-juice.jpg"},{"id":2036,"name":"rosemary","localizedName":"rosemary","image":"rosemary.jpg"},{"id":11529,"name":"tomato","localizedName":"tomato","image":"tomato.png"},{"id":11215,"name":"garlic","localizedName":"garlic","image":"garlic.png"},{"id":11959,"name":"arugula","localizedName":"arugula","image":"arugula-or-rocket-salad.jpg"},{"id":0,"name":"beans","localizedName":"beans","image":"kidney-beans.jpg"},{"id":11282,"name":"onion","localizedName":"onion","image":"brown-onion.png"},{"id":10015121,"name":"tuna","localizedName":"tuna","image":"canned-tuna.png"},{"id":4582,"name":"cooking oil","localizedName":"cooking oil","image":"vegetable-oil.jpg"}],"equipment":[{"id":404783,"name":"bowl","localizedName":"bowl","image":"bowl.jpg"}],"length":{"number":30,"unit":"minutes"}},{"number":2,"step":"Put the oil, lemon juice, mustard, honey and salt and pepper in a screw top jar. Seal and put aside.","ingredients":[{"id":1102047,"name":"salt and pepper","localizedName":"salt and pepper","image":"salt-and-pepper.jpg"},{"id":9152,"name":"lemon juice","localizedName":"lemon juice","image":"lemon-juice.jpg"},{"id":2046,"name":"mustard","localizedName":"mustard","image":"regular-mustard.jpg"},{"id":19296,"name":"honey","localizedName":"honey","image":"honey.png"},{"id":4582,"name":"cooking oil","localizedName":"cooking oil","image":"vegetable-oil.jpg"}],"equipment":[]},{"number":3,"step":"Heat a cast iron ridged grill pan or frying pan until very hot. Cook the tuna on a moderately high heat for 2 minutes each side  dont overcook or it will be dry.Shake the dressing.","ingredients":[{"id":0,"name":"shake","localizedName":"shake","image":""},{"id":10015121,"name":"tuna","localizedName":"tuna","image":"canned-tuna.png"}],"equipment":[{"id":404645,"name":"frying pan","localizedName":"frying pan","image":"pan.png"},{"id":404648,"name":"grill pan","localizedName":"grill pan","image":"grill-pan.jpg"}],"length":{"number":2,"unit":"minutes"}},{"number":4,"step":"Pour over the salad.","ingredients":[],"equipment":[]},{"number":5,"step":"Mix.","ingredients":[],"equipment":[]},{"number":6,"step":"Serve the salad with the tuna on top.","ingredients":[{"id":10015121,"name":"tuna","localizedName":"tuna","image":"canned-tuna.png"}],"equipment":[]}]}]
