[{"name":"","steps":[{"number":1,"step":"Stir together preserved lemon rind, 2 tbsp. lemon juice, and the oil in a small bowl. Season with salt, pepper, and more lemon juice if needed.","ingredients":[{"id":99093,"name":"preserved lemon","localizedName":"preserved lemon","image":"lemon.png"},{"id":9152,"name":"lemon juice","localizedName":"lemon juice","image":"lemon-juice.jpg"},{"id":1002030,"name":"pepper","localizedName":"pepper","image":"pepper.jpg"},{"id":23572,"name":"beef","localizedName":"beef","image":"beef-cubes-raw.png"},{"id":2047,"name":"salt","localizedName":"salt","image":"salt.jpg"},{"id":4582,"name":"cooking oil","localizedName":"cooking oil","image":"vegetable-oil.jpg"}],"equipment":[{"id":404783,"name":"bowl","localizedName":"bowl","image":"bowl.jpg"}]},{"number":2,"step":"Slice celery stalks very thinly on the diagonal, using a mandoline or sharp knife.","ingredients":[{"id":10111143,"name":"celery rib","localizedName":"celery sticks","image":"celery.jpg"}],"equipment":[{"id":404687,"name":"mandoline","localizedName":"mandoline","image":"mandoline-slicer.png"},{"id":404745,"name":"knife","localizedName":"knife","image":"chefs-knife.jpg"}]},{"number":3,"step":"Cut fennel bulbs in half lengthwise; cut out and discard cores. Thinly slice crosswise. Pit dates and cut into slivers.","ingredients":[{"id":11957,"name":"fennel bulb","localizedName":"fennel bulb","image":"fennel.png"},{"id":9087,"name":"dates","localizedName":"dates","image":"dates.jpg"}],"equipment":[]},{"number":4,"step":"Combine with celery, fennel, and parsley in a large bowl.","ingredients":[{"id":11297,"name":"parsley","localizedName":"parsley","image":"parsley.jpg"},{"id":11143,"name":"celery","localizedName":"celery","image":"celery.jpg"},{"id":11957,"name":"fennel","localizedName":"fennel","image":"fennel.png"}],"equipment":[{"id":404783,"name":"bowl","localizedName":"bowl","image":"bowl.jpg"}]},{"number":5,"step":"Add dressing and toss to coat.","ingredients":[],"equipment":[]}]}]
