[{"name":"","steps":[{"number":1,"step":"Place flour in flat bowl. (for coating filets).Stir lime juice and liquid egg together and put in its own bowl.","ingredients":[{"id":9160,"name":"lime juice","localizedName":"lime juice","image":"lime-juice.png"},{"id":20081,"name":"all purpose flour","localizedName":"all purpose flour","image":"flour.png"},{"id":1123,"name":"egg","localizedName":"egg","image":"egg.png"}],"equipment":[{"id":404783,"name":"bowl","localizedName":"bowl","image":"bowl.jpg"}]},{"number":2,"step":"Mix breadcrumbs and coconut together.","ingredients":[{"id":18079,"name":"breadcrumbs","localizedName":"breadcrumbs","image":"breadcrumbs.jpg"},{"id":12104,"name":"coconut","localizedName":"coconut","image":"coconut.jpg"}],"equipment":[]},{"number":3,"step":"Add salt, pepper, Basil, garlic salt and place in a flat bowl.With each filet, cover in flour, shake off excess, dip in egg/lime mix, and coat both sides with the breadcrumbs/coconut.","ingredients":[{"id":18079,"name":"breadcrumbs","localizedName":"breadcrumbs","image":"breadcrumbs.jpg"},{"id":1062047,"name":"garlic salt","localizedName":"garlic salt","image":"garlic-salt.jpg"},{"id":12104,"name":"coconut","localizedName":"coconut","image":"coconut.jpg"},{"id":1002030,"name":"pepper","localizedName":"pepper","image":"pepper.jpg"},{"id":2044,"name":"basil","localizedName":"basil","image":"basil.jpg"},{"id":20081,"name":"all purpose flour","localizedName":"all purpose flour","image":"flour.png"},{"id":0,"name":"shake","localizedName":"shake","image":""},{"id":9159,"name":"lime","localizedName":"lime","image":"lime.jpg"},{"id":2047,"name":"salt","localizedName":"salt","image":"salt.jpg"},{"id":0,"name":"dip","localizedName":"dip","image":""},{"id":1123,"name":"egg","localizedName":"egg","image":"egg.png"}],"equipment":[{"id":404783,"name":"bowl","localizedName":"bowl","image":"bowl.jpg"}]},{"number":4,"step":"Place on a cookie sheet that has been sprayed with cooking spray.","ingredients":[{"id":4679,"name":"cooking spray","localizedName":"cooking spray","image":"cooking-spray.png"},{"id":10118192,"name":"cookies","localizedName":"cookies","image":"shortbread-cookies.jpg"}],"equipment":[{"id":404727,"name":"baking sheet","localizedName":"baking sheet","image":"baking-sheet.jpg"}]},{"number":5,"step":"Bake @ 375 for 15 min (or until it flakes).I served with a Broccoli & Rice dish, and steamed zucchini.","ingredients":[{"id":11090,"name":"broccoli","localizedName":"broccoli","image":"broccoli.jpg"},{"id":11477,"name":"zucchini","localizedName":"zucchini","image":"zucchini.jpg"},{"id":20444,"name":"rice","localizedName":"rice","image":"uncooked-white-rice.png"}],"equipment":[{"id":404784,"name":"oven","localizedName":"oven","image":"oven.jpg"}],"length":{"number":15,"unit":"minutes"}}]}]
