[{"name":"","steps":[{"number":1,"step":"Assemble galette: Preheat the oven to 400 F.","ingredients":[],"equipment":[{"id":404784,"name":"oven","localizedName":"oven","image":"oven.jpg","temperature":{"number":400.0,"unit":"Fahrenheit"}}]},{"number":2,"step":"Roll the dough into a large thin circle and set it on the back of a sheet pan or cookie sheet. The edges will hang over the sides.","ingredients":[{"id":10118192,"name":"cookies","localizedName":"cookies","image":"shortbread-cookies.jpg"},{"id":0,"name":"dough","localizedName":"dough","image":"pizza-dough"},{"id":0,"name":"roll","localizedName":"roll","image":"dinner-yeast-rolls.jpg"}],"equipment":[{"id":404727,"name":"baking sheet","localizedName":"baking sheet","image":"baking-sheet.jpg"},{"id":404645,"name":"frying pan","localizedName":"frying pan","image":"pan.png"}]},{"number":3,"step":"Add the filling, making a mound 7 to 8 inches across, then fold the edges over and brush with the melted butter.","ingredients":[{"id":1001,"name":"butter","localizedName":"butter","image":"butter-sliced.jpg"}],"equipment":[]},{"number":4,"step":"Pour any extra butter into the vegetables.","ingredients":[{"id":11583,"name":"vegetable","localizedName":"vegetable","image":"mixed-vegetables.png"},{"id":1001,"name":"butter","localizedName":"butter","image":"butter-sliced.jpg"}],"equipment":[]},{"number":5,"step":"Bake until browned, 25 to 30 minutes. While it is baking, mix the horseradish and cream to form a sauce, and season to taste. When galette is done, carefully slide it onto a serving plate.","ingredients":[{"id":1002055,"name":"horseradish","localizedName":"horseradish","image":"horseradish.jpg"},{"id":1053,"name":"cream","localizedName":"cream","image":"fluid-cream.jpg"},{"id":0,"name":"sauce","localizedName":"sauce","image":""}],"equipment":[{"id":404784,"name":"oven","localizedName":"oven","image":"oven.jpg"}],"length":{"number":25,"unit":"minutes"}},{"number":6,"step":"Serve with the horseradish sauce on the side.See more: Cabbage, Mushrooms, Photo, Tarts/Quiche, Vegetarian","ingredients":[{"id":2055,"name":"horseradish sauce","localizedName":"horseradish sauce","image":"horseradish-sauce.jpg"},{"id":11260,"name":"mushrooms","localizedName":"mushrooms","image":"mushrooms.png"},{"id":11109,"name":"cabbage","localizedName":"cabbage","image":"cabbage.jpg"}],"equipment":[]},{"number":7,"step":"Do more: Link | Bookmark| Pin | Print| Email| 115 Comments","ingredients":[],"equipment":[]}]}]
