[{"name":"","steps":[{"number":1,"step":"Heat a pot of water to a boil, salt the water and cook pasta to al dente.","ingredients":[{"id":20420,"name":"pasta","localizedName":"pasta","image":"fusilli.jpg"},{"id":14412,"name":"water","localizedName":"water","image":"water.png"},{"id":2047,"name":"salt","localizedName":"salt","image":"salt.jpg"}],"equipment":[{"id":404752,"name":"pot","localizedName":"pot","image":"stock-pot.jpg"}]},{"number":2,"step":"Heat a deep large skillet with 1 tablespoon extra-virgin olive oil over medium-high heat.","ingredients":[{"id":1034053,"name":"extra virgin olive oil","localizedName":"extra virgin olive oil","image":"olive-oil.jpg"}],"equipment":[{"id":404645,"name":"frying pan","localizedName":"frying pan","image":"pan.png"}]},{"number":3,"step":"Add bacon and crisp 3 to 4 minutes.","ingredients":[{"id":10123,"name":"bacon","localizedName":"bacon","image":"raw-bacon.png"}],"equipment":[],"length":{"number":3,"unit":"minutes"}},{"number":4,"step":"Add onions, garlic, bay leaf and mushrooms, season with salt and pepper and cook until tender but not browned, 5 minutes.","ingredients":[{"id":1102047,"name":"salt and pepper","localizedName":"salt and pepper","image":"salt-and-pepper.jpg"},{"id":11260,"name":"mushrooms","localizedName":"mushrooms","image":"mushrooms.png"},{"id":2004,"name":"bay leaves","localizedName":"bay leaves","image":"bay-leaves.jpg"},{"id":11215,"name":"garlic","localizedName":"garlic","image":"garlic.png"},{"id":11282,"name":"onion","localizedName":"onion","image":"brown-onion.png"}],"equipment":[],"length":{"number":5,"unit":"minutes"}},{"number":5,"step":"Add tomatoes, crush them up with a wooden spoon and simmer 15 minutes on low heat.","ingredients":[{"id":11529,"name":"tomato","localizedName":"tomato","image":"tomato.png"}],"equipment":[{"id":404732,"name":"wooden spoon","localizedName":"wooden spoon","image":"wooden-spoon.jpg"}],"length":{"number":15,"unit":"minutes"}},{"number":6,"step":"Season the fish with salt and pepper. Dust fish with flour and shake off excess.","ingredients":[{"id":1102047,"name":"salt and pepper","localizedName":"salt and pepper","image":"salt-and-pepper.jpg"},{"id":20081,"name":"all purpose flour","localizedName":"all purpose flour","image":"flour.png"},{"id":0,"name":"shake","localizedName":"shake","image":""},{"id":10115261,"name":"fish","localizedName":"fish","image":"fish-fillet.jpg"}],"equipment":[]},{"number":7,"step":"Heat 2 tablespoons extra-virgin olive oil in a large skillet over medium high heat. Cook fish 4 minutes on each side.","ingredients":[{"id":1034053,"name":"extra virgin olive oil","localizedName":"extra virgin olive oil","image":"olive-oil.jpg"},{"id":10115261,"name":"fish","localizedName":"fish","image":"fish-fillet.jpg"}],"equipment":[{"id":404645,"name":"frying pan","localizedName":"frying pan","image":"pan.png"}],"length":{"number":4,"unit":"minutes"}},{"number":8,"step":"While fish cooks, stir peas into sauce, return to bubble and stir in mascarpone cheese. Adjust seasoning.","ingredients":[{"id":93820,"name":"mascarpone","localizedName":"mascarpone","image":"white-cream-fluffy.jpg"},{"id":1042027,"name":"seasoning","localizedName":"seasoning","image":"seasoning.png"},{"id":0,"name":"sauce","localizedName":"sauce","image":""},{"id":10115261,"name":"fish","localizedName":"fish","image":"fish-fillet.jpg"},{"id":11304,"name":"peas","localizedName":"peas","image":"peas.jpg"}],"equipment":[]},{"number":9,"step":"Remove fish from skillet to a platter and cover loosely with foil to keep warm. Reduce heat to medium and add butter to pan. Brown butter, 2 to 3 minutes, stir in balsamic and simmer 1 to 2 minutes to reduce by half.","ingredients":[{"id":1001,"name":"butter","localizedName":"butter","image":"butter-sliced.jpg"},{"id":10115261,"name":"fish","localizedName":"fish","image":"fish-fillet.jpg"}],"equipment":[{"id":404645,"name":"frying pan","localizedName":"frying pan","image":"pan.png"},{"id":404765,"name":"aluminum foil","localizedName":"aluminum foil","image":"aluminum-foil.png"}],"length":{"number":3,"unit":"minutes"}},{"number":10,"step":"Pour the brown butter and vinegar over fish.","ingredients":[{"id":2053,"name":"vinegar","localizedName":"vinegar","image":"vinegar-(white).jpg"},{"id":1001,"name":"butter","localizedName":"butter","image":"butter-sliced.jpg"},{"id":10115261,"name":"fish","localizedName":"fish","image":"fish-fillet.jpg"}],"equipment":[]},{"number":11,"step":"Drain pasta, toss with sauce and wilt basil into pasta.","ingredients":[{"id":2044,"name":"basil","localizedName":"basil","image":"basil.jpg"},{"id":20420,"name":"pasta","localizedName":"pasta","image":"fusilli.jpg"},{"id":0,"name":"sauce","localizedName":"sauce","image":""}],"equipment":[]},{"number":12,"step":"Serve fish with pasta alongside.","ingredients":[{"id":20420,"name":"pasta","localizedName":"pasta","image":"fusilli.jpg"},{"id":10115261,"name":"fish","localizedName":"fish","image":"fish-fillet.jpg"}],"equipment":[]}]}]
