[{"name":"","steps":[{"number":1,"step":"Preheat oven to 35","ingredients":[],"equipment":[{"id":404784,"name":"oven","localizedName":"oven","image":"oven.jpg"}]},{"number":2,"step":"Butter a 1-quart ovenproof dish, and set aside.","ingredients":[{"id":1001,"name":"butter","localizedName":"butter","image":"butter-sliced.jpg"}],"equipment":[]},{"number":3,"step":"Heat oil in a large skillet over medium heat.","ingredients":[{"id":4582,"name":"cooking oil","localizedName":"cooking oil","image":"vegetable-oil.jpg"}],"equipment":[{"id":404645,"name":"frying pan","localizedName":"frying pan","image":"pan.png"}]},{"number":4,"step":"Add onion, and saut 3 to 4 minutes or until soft and translucent.","ingredients":[{"id":11282,"name":"onion","localizedName":"onion","image":"brown-onion.png"}],"equipment":[],"length":{"number":3,"unit":"minutes"}},{"number":5,"step":"Combine onion, artichoke, and next 9 ingredients in a large bowl, add sea salt and pepper, and stir to combine thoroughly.","ingredients":[{"id":1102047,"name":"salt and pepper","localizedName":"salt and pepper","image":"salt-and-pepper.jpg"},{"id":11007,"name":"artichoke","localizedName":"artichoke","image":"artichokes.png"},{"id":11282,"name":"onion","localizedName":"onion","image":"brown-onion.png"}],"equipment":[{"id":404783,"name":"bowl","localizedName":"bowl","image":"bowl.jpg"}]},{"number":6,"step":"Transfer to prepared dish, and bake at 350 for 30 to 35 minutes or until heated through and bubbling around edges.","ingredients":[],"equipment":[{"id":404784,"name":"oven","localizedName":"oven","image":"oven.jpg"}],"length":{"number":30,"unit":"minutes"}},{"number":7,"step":"Serve warm with Belgian endive, crostini, or crackers.","ingredients":[{"id":11151,"name":"belgian endive","localizedName":"belgian endive","image":"chicory.jpg"},{"id":18621,"name":"crackers","localizedName":"crackers","image":"crackers.jpg"},{"id":10018033,"name":"crostini","localizedName":"crostini","image":"sliced-baguette-or-crostini.jpg"}],"equipment":[]}]}]
