[{"name":"","steps":[{"number":1,"step":"Bring a large pot of salted water to a boil over high heat.","ingredients":[{"id":14412,"name":"water","localizedName":"water","image":"water.png"}],"equipment":[{"id":404752,"name":"pot","localizedName":"pot","image":"stock-pot.jpg"}]},{"number":2,"step":"Add the brussels sprouts and cook until just tender, about 7 minutes.","ingredients":[{"id":11098,"name":"brussels sprouts","localizedName":"brussels sprouts","image":"brussels-sprouts.jpg"}],"equipment":[],"length":{"number":7,"unit":"minutes"}},{"number":3,"step":"Drain well.","ingredients":[],"equipment":[]},{"number":4,"step":"Meanwhile, in a large deep skillet, cook the bacon over moderate heat until crisp, about 5 minutes.","ingredients":[{"id":10123,"name":"bacon","localizedName":"bacon","image":"raw-bacon.png"}],"equipment":[{"id":404645,"name":"frying pan","localizedName":"frying pan","image":"pan.png"}],"length":{"number":5,"unit":"minutes"}},{"number":5,"step":"Add the butter. When the foam subsides, add the brussels sprouts and cook over moderate heat, stirring occasionally, until they are lightly browned, about 5 minutes.","ingredients":[{"id":11098,"name":"brussels sprouts","localizedName":"brussels sprouts","image":"brussels-sprouts.jpg"},{"id":1001,"name":"butter","localizedName":"butter","image":"butter-sliced.jpg"}],"equipment":[],"length":{"number":5,"unit":"minutes"}},{"number":6,"step":"Add the chestnuts and season with salt and pepper.","ingredients":[{"id":1102047,"name":"salt and pepper","localizedName":"salt and pepper","image":"salt-and-pepper.jpg"},{"id":12098,"name":"chestnuts","localizedName":"chestnuts","image":"chestnuts.jpg"}],"equipment":[]},{"number":7,"step":"Add the Rich Turkey Stock, simmer until heated through and serve.","ingredients":[{"id":1006172,"name":"turkey stock","localizedName":"turkey stock","image":"chicken-broth.png"}],"equipment":[]}]}]
