[{"name":"","steps":[{"number":1,"step":"If using bamboo skewers, soak skewers in water at least 30 minutes. Prepare outdoor grill for direct grilling on medium-high.In blender, puree cilantro, sour cream, mayonnaise, 2 tablespoons lemon juice, vinegar, 1/4 teaspoon salt, and 1/2 teaspoon freshly ground black pepper; set dressing aside.In large bowl, combine shrimp, oil, coriander, remaining 2 tablespoons lemon juice, 1/8 teaspoon salt, and 1/4 teaspoon freshly ground black pepper, tossing until well coated.Thread shrimp, 1/2 inch apart, on skewers. Grill 3 to 4 minutes or until shrimp just turn opaque, turning over once.","ingredients":[{"id":1002030,"name":"ground black pepper","localizedName":"ground black pepper","image":"pepper.jpg"},{"id":9152,"name":"lemon juice","localizedName":"lemon juice","image":"lemon-juice.jpg"},{"id":4025,"name":"mayonnaise","localizedName":"mayonnaise","image":"mayonnaise.png"},{"id":1056,"name":"sour cream","localizedName":"sour cream","image":"sour-cream.jpg"},{"id":1012013,"name":"coriander","localizedName":"coriander","image":"ground-coriander.jpg"},{"id":11165,"name":"cilantro","localizedName":"cilantro","image":"cilantro.png"},{"id":2053,"name":"vinegar","localizedName":"vinegar","image":"vinegar-(white).jpg"},{"id":15270,"name":"shrimp","localizedName":"shrimp","image":"shrimp.png"},{"id":14412,"name":"water","localizedName":"water","image":"water.png"},{"id":2047,"name":"salt","localizedName":"salt","image":"salt.jpg"},{"id":4582,"name":"cooking oil","localizedName":"cooking oil","image":"vegetable-oil.jpg"}],"equipment":[{"id":404726,"name":"blender","localizedName":"blender","image":"blender.png"},{"id":3065,"name":"skewers","localizedName":"skewers","image":"wooden-skewers.jpg"},{"id":404706,"name":"grill","localizedName":"grill","image":"grill.jpg"},{"id":404783,"name":"bowl","localizedName":"bowl","image":"bowl.jpg"}],"length":{"number":33,"unit":"minutes"}},{"number":2,"step":"Transfer to plate.In another large bowl, toss lettuce with half of dressing until well coated. Divide among 4 serving plates. In same bowl, toss tomatoes and apple with half of remaining dressing until well coated; place on lettuce with shrimp.","ingredients":[{"id":11529,"name":"tomato","localizedName":"tomato","image":"tomato.png"},{"id":11252,"name":"lettuce","localizedName":"lettuce","image":"iceberg-lettuce.jpg"},{"id":15270,"name":"shrimp","localizedName":"shrimp","image":"shrimp.png"},{"id":9003,"name":"apple","localizedName":"apple","image":"apple.jpg"}],"equipment":[{"id":404783,"name":"bowl","localizedName":"bowl","image":"bowl.jpg"}]},{"number":3,"step":"Drizzle with remaining dressing.","ingredients":[],"equipment":[]}]}]
