[{"name":"","steps":[{"number":1,"step":"Combine first 6 ingredients in a large bowl; stir with a whisk.","ingredients":[],"equipment":[{"id":404661,"name":"whisk","localizedName":"whisk","image":"whisk.png"},{"id":404783,"name":"bowl","localizedName":"bowl","image":"bowl.jpg"}]},{"number":2,"step":"Add arugula and pears to bowl; toss to coat.","ingredients":[{"id":11959,"name":"arugula","localizedName":"arugula","image":"arugula-or-rocket-salad.jpg"},{"id":9252,"name":"pear","localizedName":"pear","image":"pears-bosc.jpg"}],"equipment":[{"id":404783,"name":"bowl","localizedName":"bowl","image":"bowl.jpg"}]},{"number":3,"step":"Place about 1 1/2 cups salad on each of 4 plates; sprinkle each serving with 1 tablespoon walnuts.","ingredients":[{"id":12155,"name":"walnuts","localizedName":"walnuts","image":"walnuts.jpg"}],"equipment":[]}]}]
