[{"name":"","steps":[{"number":1,"step":"Preheat oven to 45","ingredients":[],"equipment":[{"id":404784,"name":"oven","localizedName":"oven","image":"oven.jpg"}]},{"number":2,"step":"Place bread in a food processor; pulse until fine crumbs measure 1 cup.","ingredients":[{"id":18064,"name":"bread","localizedName":"bread","image":"white-bread.jpg"}],"equipment":[{"id":404771,"name":"food processor","localizedName":"food processor","image":"food-processor.png"}]},{"number":3,"step":"Combine breadcrumbs, parsley, and garlic.","ingredients":[{"id":18079,"name":"breadcrumbs","localizedName":"breadcrumbs","image":"breadcrumbs.jpg"},{"id":11297,"name":"parsley","localizedName":"parsley","image":"parsley.jpg"},{"id":11215,"name":"garlic","localizedName":"garlic","image":"garlic.png"}],"equipment":[]},{"number":4,"step":"Heat 2 teaspoons butter and 2 teaspoons oil in a large skillet over medium-high heat.","ingredients":[{"id":1001,"name":"butter","localizedName":"butter","image":"butter-sliced.jpg"},{"id":4582,"name":"cooking oil","localizedName":"cooking oil","image":"vegetable-oil.jpg"}],"equipment":[{"id":404645,"name":"frying pan","localizedName":"frying pan","image":"pan.png"}]},{"number":5,"step":"Add breadcrumb mixture; cook 3 minutes or until golden brown and garlic is fragrant, stirring frequently.","ingredients":[{"id":18079,"name":"breadcrumbs","localizedName":"breadcrumbs","image":"breadcrumbs.jpg"},{"id":11215,"name":"garlic","localizedName":"garlic","image":"garlic.png"}],"equipment":[],"length":{"number":3,"unit":"minutes"}},{"number":6,"step":"Coat 4 individual gratin dishes with remaining 2 teaspoons oil. Arrange shrimp in a single layer in dishes; sprinkle with dash of salt and dash of pepper.","ingredients":[{"id":1002030,"name":"pepper","localizedName":"pepper","image":"pepper.jpg"},{"id":15270,"name":"shrimp","localizedName":"shrimp","image":"shrimp.png"},{"id":2047,"name":"salt","localizedName":"salt","image":"salt.jpg"},{"id":4582,"name":"cooking oil","localizedName":"cooking oil","image":"vegetable-oil.jpg"}],"equipment":[]},{"number":7,"step":"Sprinkle with 1/2 cup breadcrumb mixture; top with tomato slices.","ingredients":[{"id":10511529,"name":"tomato slices","localizedName":"tomato slices","image":"sliced-tomato.jpg"},{"id":18079,"name":"breadcrumbs","localizedName":"breadcrumbs","image":"breadcrumbs.jpg"}],"equipment":[]},{"number":8,"step":"Sprinkle with remaining dash of salt and dash of pepper. Top with remaining 1/2 cup breadcrumb mixture; dot with remaining 2 teaspoons butter.","ingredients":[{"id":18079,"name":"breadcrumbs","localizedName":"breadcrumbs","image":"breadcrumbs.jpg"},{"id":1001,"name":"butter","localizedName":"butter","image":"butter-sliced.jpg"},{"id":1002030,"name":"pepper","localizedName":"pepper","image":"pepper.jpg"},{"id":2047,"name":"salt","localizedName":"salt","image":"salt.jpg"}],"equipment":[]},{"number":9,"step":"Bake at 450 for 12 minutes or until the shrimp are done.","ingredients":[{"id":15270,"name":"shrimp","localizedName":"shrimp","image":"shrimp.png"}],"equipment":[{"id":404784,"name":"oven","localizedName":"oven","image":"oven.jpg"}],"length":{"number":12,"unit":"minutes"}},{"number":10,"step":"Drizzle with vinegar.","ingredients":[{"id":2053,"name":"vinegar","localizedName":"vinegar","image":"vinegar-(white).jpg"}],"equipment":[]}]}]
