[{"name":"","steps":[{"number":1,"step":"Preheat oven to 450 degrees. Turn a large baking sheet upside down; rub with oil. Using your hands, crush tomatoes into a pulp in a small bowl; season with salt and pepper.","ingredients":[{"id":1102047,"name":"salt and pepper","localizedName":"salt and pepper","image":"salt-and-pepper.jpg"},{"id":11529,"name":"tomato","localizedName":"tomato","image":"tomato.png"},{"id":4582,"name":"cooking oil","localizedName":"cooking oil","image":"vegetable-oil.jpg"},{"id":1012034,"name":"dry seasoning rub","localizedName":"dry seasoning rub","image":"seasoning.png"}],"equipment":[{"id":404727,"name":"baking sheet","localizedName":"baking sheet","image":"baking-sheet.jpg"},{"id":404783,"name":"bowl","localizedName":"bowl","image":"bowl.jpg"},{"id":404784,"name":"oven","localizedName":"oven","image":"oven.jpg"}]}]}]
